{
  "lang": "zh",
  "title": "主必再來",
  "num": "490",
  "verses": [
    {
      "num": 1,
      "label": "1",
      "html": "(一)<br>主再來，諸天將<br>大放光明，<br>不再有眼淚憂愁。<br>主再來，<br>榮光要普照宇宙，<br>黑夜將變成白晝。"
    },
    {
      "num": 1,
      "label": "1C",
      "html": "(一)<br>主必再來，<br>我主必再來，<br>將要見主的光彩。<br>主再來，<br>眾聖徒都要改變，<br>永遠與救主同在。"
    },
    {
      "num": 2,
      "label": "2",
      "html": "(二)<br>主再來，那時候<br>祂已預定，<br>我救主親自降臨。<br>主再來，<br>祂權柄旨意成全，<br>得勝利救恩完成。"
    },
    {
      "num": 2,
      "label": "2C",
      "html": "(二)<br>主必再來，<br>我主必再來，<br>將要見主的光彩。<br>主再來，<br>眾聖徒都要改變，<br>永遠與救主同在。"
    },
    {
      "num": 3,
      "label": "3",
      "html": "(三)<br>主再來，我主就<br>必快再來！<br>污穢與罪惡不再。<br>主再來，<br>我主就必快再來。<br>你是否做好安排？"
    },
    {
      "num": 3,
      "label": "3C",
      "html": "(三)<br>主必再來，<br>我主必再來，<br>將要見主的光彩。<br>主再來，<br>眾聖徒都要改變，<br>永遠與救主同在。"
    }
  ]
}