{
  "lang": "en",
  "num": "17",
  "title": "The Half Has Never Been Told",
  "verses": [
    {
      "label": "1",
      "num": 1,
      "html": "1<br><b>I</b> know I love Thee better, Lord, <br><b>T</b>han any earthly joy; <br><b>F</b>or Thou hast given me the peace <br><b>W</b>hich nothing can destroy."
    },
    {
      "label": "1C",
      "num": 1,
      "html": "<b>1</b><br><b>T</b>he half has never yet been told, <br><b>O</b>f love so full and free! <br><b>T</b>he half has never yet been told, <br><b>T</b>he blood, it cleanseth me!"
    },
    {
      "label": "2",
      "num": 2,
      "html": "2<br><b>I</b> know that Thou art nearer still <br><b>T</b>han any earthly throng; <br><b>A</b>nd sweeter is the thought of Thee <br><b>T</b>han any lovely song."
    },
    {
      "label": "2C",
      "num": 2,
      "html": "<b>2</b><br><b>T</b>he half has never yet been told, <br><b>O</b>f love so full and free! <br><b>T</b>he half has never yet been told, <br><b>T</b>he blood, it cleanseth me!"
    },
    {
      "label": "3",
      "num": 3,
      "html": "3<br><b>T</b>hou hast put gladness in my heart; <br><b>T</b>hen may I well be glad! <br><b>W</b>ithout the secret of Thy love <br><b>I</b> could not but be sad."
    },
    {
      "label": "3C",
      "num": 3,
      "html": "<b>3</b><br><b>T</b>he half has never yet been told, <br><b>O</b>f love so full and free! <br><b>T</b>he half has never yet been told, <br><b>T</b>he blood, it cleanseth me!"
    },
    {
      "label": "4",
      "num": 4,
      "html": "4<br><b>O</b> Saviour, precious Saviour mine! <br><b>W</b>hat will Thy presence be, <br><b>I</b>f such a life of joy can crown <br><b>O</b>ur walk on earth with Thee?"
    },
    {
      "label": "4C",
      "num": 4,
      "html": "<b>4</b><br><b>T</b>he half has never yet been told, <br><b>O</b>f love so full and free! <br><b>T</b>he half has never yet been told, <br><b>T</b>he blood, it cleanseth me!"
    }
  ]
}