{
  "lang": "en",
  "num": "44",
  "title": "Weeping Will Not Save Me!",
  "verses": [
    {
      "label": "1",
      "num": 1,
      "html": "1<br><b>W</b>eeping will not save me! <br><b>T</b>hough my face were bathed in tears, <br><b>T</b>hat could not allay my fears, <br><b>C</b>ould not wash the sins of years! <br><b>W</b>eeping will not save me. <br><b>J</b>esus wept and died for me; <br><b>J</b>esus suffered on the tree: <br><b>J</b>esus waits to make me free; <br><b>H</b>e alone can save me!"
    },
    {
      "label": "2",
      "num": 2,
      "html": "2<br><b>W</b>orking will not save me! <br><b>P</b>urest deeds that I can do, <br><b>H</b>oliest thoughts and feelings too, <br><b>C</b>annot form my soul anew! <br><b>W</b>orking will not save me. <br><b>J</b>esus wept and died for me; <br><b>J</b>esus suffered on the tree: <br><b>J</b>esus waits to make me free; <br><b>H</b>e alone can save me!"
    },
    {
      "label": "3",
      "num": 3,
      "html": "3<br><b>W</b>aiting will not save me! <br><b>H</b>elpless, guilty, lost, I lie; <br><b>I</b>n my ear is Mercy’s cry; <br><b>I</b>f I wait I can but die: <br><b>W</b>aiting will not save me. <br><b>J</b>esus wept and died for me; <br><b>J</b>esus suffered on the tree: <br><b>J</b>esus waits to make me free; <br><b>H</b>e alone can save me!"
    },
    {
      "label": "4",
      "num": 4,
      "html": "4<br><b>F</b>aith in Christ will save me! <br><b>L</b>et me trust Thy weeping Son, <br><b>T</b>rust the work that He has done; <br><b>T</b>o His arms, Lord, help me run: <br><b>F</b>aith in Christ will save me. <br><b>J</b>esus wept and died for me; <br><b>J</b>esus suffered on the tree: <br><b>J</b>esus waits to make me free; <br><b>H</b>e alone can save me!"
    }
  ]
}