{
  "lang": "en",
  "num": "465",
  "title": "Go Tell It on the Mountain",
  "verses": [
    {
      "label": "1",
      "num": 1,
      "html": "1<br><b>G</b>o tell it on the mountain, <br><b>O</b>ver the hills and ev’rywhere; <br><b>G</b>o tell it on the mountain, <br><b>T</b>hat Jesus Christ is born!"
    },
    {
      "label": "1C",
      "num": 1,
      "html": "<b>1</b><br><b>W</b>hen I was a seeker, I sought both night and day; <br><b>I</b> asked the Lord to help me, <br><b>a</b>nd He showed me the way. <br><b>G</b>o tell it on the mountain, <br><b>O</b>ver the hills and ev’rywhere; <br><b>G</b>o tell it on the mountain, <br><b>T</b>hat Jesus Christ is born! "
    },
    {
      "label": "2",
      "num": 2,
      "html": "2<br><b>G</b>o tell it on the mountain, <br><b>O</b>ver the hills and ev’rywhere; <br><b>G</b>o tell it on the mountain, <br><b>T</b>hat Jesus Christ is born!"
    },
    {
      "label": "2C",
      "num": 2,
      "html": "<b>2</b><br><b>H</b>e made me a watchman Upon a city wall,<br><b>A</b>nd if I am a Christian,<br><b>I</b> am the least of all.<br><b>G</b>o tell it on the mountain,<br><b>O</b>ver the hills and ev’rywhere;<br><b>G</b>o tell it on the mountain,<br><b>T</b>hat Jesus Christ is born!"
    }
  ]
}