{
  "lang": "en",
  "num": "49",
  "title": "All the Way to Calvary",
  "verses": [
    {
      "label": "1",
      "num": 1,
      "html": "1<br><b>O</b>h, how dark the night that wrapt my spirit round! Oh, how deep the woe my Saviour found <br><b>W</b>hen His blessed sunshine flooded all my soul, <br><b>B</b>ade the darkness vanish: made me whole! "
    },
    {
      "label": "1C",
      "num": 1,
      "html": "<b>1</b><br><b>A</b>ll the way to Calvary He went for me, <br><b>H</b>e went for me, <br><b>H</b>e went for me; <br><b>A</b>ll the way to Calvary He went for me, <br><b>H</b>e died to set me free."
    },
    {
      "label": "2",
      "num": 2,
      "html": "2<br><b>T</b>remblingly a sinner bowed before His face, <br><b>N</b>aught I knew of pardon nor His grace, <br><b>H</b>eard a voice so tender: “Cease thy wild regret- <br><b>I</b> have bought thy pardon, paid thy debt.” "
    },
    {
      "label": "2C",
      "num": 2,
      "html": "<b>2</b><br><b>A</b>ll the way to Calvary He went for me, <br><b>H</b>e went for me, <br><b>H</b>e went for me; <br><b>A</b>ll the way to Calvary He went for me, <br><b>H</b>e died to set me free."
    },
    {
      "label": "3",
      "num": 3,
      "html": "3<br><b>O</b>h, ’twas wondrous love the Saviour showed for me, When He left His throne for Calvary, <br><b>W</b>hen He trod the winepress, trod it all alone: <br><b>P</b>raise His name forever- make it known. "
    },
    {
      "label": "3C",
      "num": 3,
      "html": "<b>3</b><br><b>A</b>ll the way to Calvary He went for me, <br><b>H</b>e went for me, <br><b>H</b>e went for me; <br><b>A</b>ll the way to Calvary He went for me, <br><b>H</b>e died to set me free."
    }
  ]
}