{
  "lang": "en",
  "num": "513",
  "title": "Springs of Living Water",
  "verses": [
    {
      "label": "1",
      "num": 1,
      "html": "1<br><b>I</b> thirsted in the barren land of sin and shame, <br><b>A</b>nd nothing satisfying there I found; <br><b>B</b>ut to the blessed cross of Christ one day I came, <br><b>W</b>here springs of living water did abound. "
    },
    {
      "label": "1C",
      "num": 1,
      "html": "<b>1</b><br><b>D</b>rinking at the spings of living water, <br><b>H</b>appy now am I, My soul they satisfy; <br><b>D</b>rinking at the springs of living water, <br><b>O</b> wonderful and bountiful supply!"
    },
    {
      "label": "2",
      "num": 2,
      "html": "2<br><b>H</b>ow sweet the living water from the hills of God,<br><b>I</b>t makes me glad and happy all the way;<br><b>N</b>ow glory, grace, and blessing mark the path I’ve trod,<br><b>I</b>’m shouting “Hallelujah” ev'ry day."
    },
    {
      "label": "2C",
      "num": 2,
      "html": "<b>2</b><br><b>D</b>rinking at the spings of living water, <br><b>H</b>appy now am I, My soul they satisfy; <br><b>D</b>rinking at the springs of living water, <br><b>O</b> wonderful and bountiful supply!"
    },
    {
      "label": "3",
      "num": 3,
      "html": "3<br><b>O</b> sinner, won’t you come today to Calvary?<br><b>A</b> fountain there is flowing deep and wide;<br><b>T</b>he Savior now invites you to the water free,<br><b>W</b>here thirsting spirits can be satisfied."
    },
    {
      "label": "3C",
      "num": 3,
      "html": "<b>3</b><br><b>D</b>rinking at the spings of living water, <br><b>H</b>appy now am I, My soul they satisfy; <br><b>D</b>rinking at the springs of living water, <br><b>O</b> wonderful and bountiful supply!"
    }
  ]
}