{
  "lang": "id",
  "num": "102",
  "oldnum": "102",
  "title": "Hidup Untuk Tuhan",
  "verses": [
    {
      "label": "1",
      "num": 1,
      "html": "1<br><b>H</b>idup untuk Kristus, <br><b>m</b>atipun bahagia; <br><b>H</b>ati slalu mendambakan, <br><b>j</b>adi hamba setia. "
    },
    {
      "label": "2",
      "num": 2,
      "html": "2<br><b>B</b>aik kepandaian, <br><b>a</b>tau kekayaan; <br><b>S</b>emuanya ku persembahkan <br><b>m</b>enjadi milikNya. "
    },
    {
      "label": "3",
      "num": 3,
      "html": "3<br><b>W</b>alaupun difitnah, <br><b>m</b>erasa kecewa; <br><b>K</b>u tetap melayani Dia, <br><b>t</b>akkan putus asa. "
    },
    {
      "label": "4",
      "num": 4,
      "html": "4<br><b>P</b>ikul salib Tuhan, <br><b>m</b>aju tak berhenti; <br><b>W</b>alau mati untuk Tuhan, <br><b>k</b>u tak akan gentar. "
    }
  ]
}