{
  "lang": "zh",
  "title": "歸家",
  "num": "456",
  "verses": [
    {
      "num": 1,
      "label": "1",
      "html": "(一)<br>高低眾多山嶺，<br>清泉雜松風，<br>我心仰望救主，<br>恬逸百慮空；<br>遙望天上青雲，<br>彼岸是樂土，"
    },
    {
      "num": 1,
      "label": "1C",
      "html": "(一)<br>我心切切渴望，<br>何時歸家中？<br>家，家，更美家；<br>我家在天上，<br>歸家樂無窮。"
    },
    {
      "num": 2,
      "label": "2",
      "html": "(二)<br>雖經過流淚谷，<br>主恩仍隆豐，<br>晨曦漸漸顯露，<br>陰影從此終；<br>我願跟從救主，<br>歸家路已通，"
    },
    {
      "num": 2,
      "label": "2C",
      "html": "(二)<br>主已戰勝惡魔，<br>前進心更雄。<br>家，家，更美家；<br>我家在天上，<br>歸家樂無窮。"
    },
    {
      "num": 3,
      "label": "3",
      "html": "(三)<br>讚美我主耶穌，<br>加恩日益隆，<br>天國路將行盡，<br>歡樂滿我衷；<br>高唱：「哈利路亞，<br>離我家已近！」"
    },
    {
      "num": 3,
      "label": "3C",
      "html": "(三)<br>仰望救主耶穌，<br>接我回家中。<br>家，家，更美家；<br>我家在天上，<br>歸家樂無窮。"
    }
  ]
}