{
  "lang": "en",
  "num": "22",
  "title": "There Is a Fountain Dear",
  "verses": [
    {
      "label": "1",
      "num": 1,
      "html": "1<br><b>T</b>here is a fountain dear, <br><b>W</b>ith water sweet and clear. <br><b>E</b>ach day at morn I’m surely bless’d, <br><b>a</b>s by God’s stream I rest. <br><b>T</b>here, far from all life’s troubling ills, <br><b>w</b>ith peaceful balm my soul He fills. "
    },
    {
      "label": "2",
      "num": 2,
      "html": "2<br><b>J</b>esus, the noblest friend, <br><b>L</b>ovingly clasps my hands, <br><b>E</b>ach day with Him, so kind and sweet, <br><b>i</b>n earnest prayer I seek. <br><b>H</b>is words mean all the world to me, <br><b>l</b>ike precious gold they’ll treasured be. "
    },
    {
      "label": "3",
      "num": 3,
      "html": "3<br><b>A</b>rmed with the Word of God, <br><b>S</b>trong shall I ever be. <br><b>F</b>rom evil’s might I’ll take no fright, <br><b>T</b>hy Spirit strengthens me. <br><b>T</b>hy Word is like a banner free, <br><b>t</b>hat leads me on to heav’n and Thee. "
    },
    {
      "label": "4",
      "num": 4,
      "html": "4<br><b>T</b>hen face to face with Thee, <br><b>I</b> see clear all my sins. <br><b>N</b>o secret thought lies unrevealed, <br><b>n</b>or hidden sin concealed. <br><b>R</b>efreshed and free I come to Thee, <br><b>T</b>hou gentle man of Galilee. "
    },
    {
      "label": "5",
      "num": 5,
      "html": "5<br><b>B</b>less’d Jesus, may Thy Word <br><b>F</b>ill me with life anew, <br><b>W</b>ith prayerful heart I’ll worship Thee <br><b>a</b>nd learn Thy ways to do. <br><b>A</b>nd so through all my earthly days, <br><b>I</b>’ll work for Thee and sing Thy praise. "
    }
  ]
}