{
  "lang": "en",
  "num": "197",
  "title": "Nor Silver Nor Gold",
  "verses": [
    {
      "label": "1",
      "num": 1,
      "html": "1<br><b>N</b>or silver nor gold hath obtained my redemption, <br><b>N</b>or riches of earth could have saved my poor soul; <br><b>T</b>he blood of the cross is my only foundation, <br><b>T</b>he death of my Savior now maketh me whole."
    },
    {
      "label": "1C",
      "num": 1,
      "html": "<b>1</b><br><b>I</b> am redeemed, but not with silver; <br><b>I</b> am bought, but not with gold; <br><b>B</b>ought with a price— the blood of Jesus, <br><b>P</b>recious price of love untold."
    },
    {
      "label": "2",
      "num": 2,
      "html": "2<br><b>N</b>or silver nor gold hath obtained my redemption, <br><b>T</b>he guilt of my conscience too heavy had grown; <br><b>T</b>he blood of the cross is my only foundation, <br><b>T</b>he death of my Savior could only atone."
    },
    {
      "label": "2C",
      "num": 2,
      "html": "<b>2</b><br><b>I</b> am redeemed, but not with silver; <br><b>I</b> am bought, but not with gold; <br><b>B</b>ought with a price— the blood of Jesus, <br><b>P</b>recious price of love untold."
    },
    {
      "label": "3",
      "num": 3,
      "html": "3<br><b>N</b>or silver nor gold hath obtained my redemption, <br><b>T</b>he holy commandment forbade me draw near; <br><b>T</b>he blood of the cross is my only foundation, <br><b>T</b>he death of my Savior removeth my fear."
    },
    {
      "label": "3C",
      "num": 3,
      "html": "<b>3</b><br><b>I</b> am redeemed, but not with silver; <br><b>I</b> am bought, but not with gold; <br><b>B</b>ought with a price— the blood of Jesus, <br><b>P</b>recious price of love untold."
    },
    {
      "label": "4",
      "num": 4,
      "html": "4<br><b>N</b>or silver nor gold hath obtained my redemption, <br><b>T</b>he way into heaven could not thus be bought; <br><b>T</b>he blood of the cross is my only foundation, <br><b>T</b>he death of my Savior redemption hath wrought."
    },
    {
      "label": "4C",
      "num": 4,
      "html": "<b>4</b><br><b>I</b> am redeemed, but not with silver; <br><b>I</b> am bought, but not with gold; <br><b>B</b>ought with a price— the blood of Jesus, <br><b>P</b>recious price of love untold."
    }
  ]
}