{
  "lang": "en",
  "num": "334",
  "title": "Jesus, Rose of Sharon",
  "verses": [
    {
      "label": "1",
      "num": 1,
      "html": "1<br><b>J</b>esus, Rose of Sharon, bloom within my heart; <br><b>B</b>eauties of Thy truth and holiness impart,"
    },
    {
      "label": "1C",
      "num": 1,
      "html": "<b>1</b><br><b>T</b>hat where’er I go my life may shed abroad <br><b>F</b>ragrance of the knowledge of the love of God."
    },
    {
      "label": "1C",
      "num": 1,
      "html": "<b>1</b><br><b>J</b>esus, Rose of Sharon, <br><b>B</b>loom in radiance and in love within my heart."
    },
    {
      "label": "2",
      "num": 2,
      "html": "2<br><b>J</b>esus, Rose of Sharon, sweeter far to see <br><b>T</b>han the fairest flow’rs of earth could ever be,"
    },
    {
      "label": "2C",
      "num": 2,
      "html": "<b>2</b><br><b>F</b>ill my life completely, adding more each day <br><b>O</b>f Thy grace divine and purity, I pray."
    },
    {
      "label": "2C",
      "num": 2,
      "html": "<b>2</b><br><b>J</b>esus, Rose of Sharon, <br><b>B</b>loom in radiance and in love within my heart."
    },
    {
      "label": "3",
      "num": 3,
      "html": "3<br><b>J</b>esus, Rose of Sharon, balm for ev’ry ill, <br><b>M</b>ay Thy tender mercy’s healing pow’r distill"
    },
    {
      "label": "3C",
      "num": 3,
      "html": "<b>3</b><br><b>F</b>or afflicted souls of weary burdened men,<br><b>G</b>iving needy mortals health and hope again."
    },
    {
      "label": "3C",
      "num": 3,
      "html": "<b>3</b><br><b>J</b>esus, Rose of Sharon, <br><b>B</b>loom in radiance and in love within my heart."
    },
    {
      "label": "4",
      "num": 4,
      "html": "4<br><b>J</b>esus, Rose of Sharon, bloom forevermore; <br><b>B</b>e Thy glory seen on earth from shore to shore,"
    },
    {
      "label": "4C",
      "num": 4,
      "html": "<b>4</b><br><b>T</b>ill the nations own Thy Sov’reignty complete, <br><b>L</b>ay their honors down and worship at Thy feet."
    },
    {
      "label": "4C",
      "num": 4,
      "html": "<b>4</b><br><b>J</b>esus, Rose of Sharon, <br><b>B</b>loom in radiance and in love within my heart."
    }
  ]
}