{
  "lang": "en",
  "num": "430",
  "title": "Shall We Gather at the River?",
  "verses": [
    {
      "label": "1",
      "num": 1,
      "html": "1<br><b>S</b>hall we gather at the river, <br><b>W</b>here bright angel feet have trod; <br><b>W</b>ith its crystal tide forever <br><b>F</b>lowing by the throne of God?"
    },
    {
      "label": "1C",
      "num": 1,
      "html": "<b>1</b><br><b>Y</b>es, we’ll gather at the river,<br><b>T</b>he beautiful, the beautiful river,<br><b>G</b>ather with the saints at the river<br><b>T</b>hat flows by the throne of God."
    },
    {
      "label": "2",
      "num": 2,
      "html": "2<br><b>O</b>n the margin of the river, <br><b>W</b>ashing up its silver spray, <br><b>W</b>e will walk and worship ever, <br><b>A</b>ll the happy golden day."
    },
    {
      "label": "2C",
      "num": 2,
      "html": "<b>2</b><br><b>Y</b>es, we’ll gather at the river,<br><b>T</b>he beautiful, the beautiful river,<br><b>G</b>ather with the saints at the river<br><b>T</b>hat flows by the throne of God."
    },
    {
      "label": "3",
      "num": 3,
      "html": "3<br><b>E</b>re we reach the shining river, <br><b>L</b>ay we ev’ry burden down; <br><b>G</b>race our spirits will deliver, <br><b>A</b>nd provide a robe and crown."
    },
    {
      "label": "3C",
      "num": 3,
      "html": "<b>3</b><br><b>Y</b>es, we’ll gather at the river,<br><b>T</b>he beautiful, the beautiful river,<br><b>G</b>ather with the saints at the river<br><b>T</b>hat flows by the throne of God."
    },
    {
      "label": "4",
      "num": 4,
      "html": "<b>4</b><br><b>S</b>oon we’ll reach the shining river,<br><b>S</b>oon our pilgrimage will cease,<br><b>S</b>oon our happy hearts will quiver<br><b>W</b>ith the melody of peace."
    },
    {
      "label": "4C",
      "num": 4,
      "html": "<b>4</b><br><b>Y</b>es, we’ll gather at the river,<br><b>T</b>he beautiful, the beautiful river,<br><b>G</b>ather with the saints at the river<br><b>T</b>hat flows by the throne of God."
    }
  ]
}
