{
  "lang": "id",
  "num": "38",
  "oldnum": "38",
  "title": "Aku Mendengar Suara Yesus",
  "verses": [
    {
      "label": "1",
      "num": 1,
      "html": "1<br><b>S</b>uara Yesus lemah lembut: “Yang lelah, datanglah! <br><b>K</b>au akan beroleh damai <br><b>s</b>erta kelegaan.”"
    },
    {
      "label": "1C",
      "num": 1,
      "html": "<b>1</b><br><b>K</b>u yang letih dan berduka, <br><b>g</b>irang mendengarnya, <br><b>S</b>ungguh bahgia di pangkuanNya, <br><b>j</b>iwaku bersuka. "
    },
    {
      "label": "2",
      "num": 2,
      "html": "2<br><b>S</b>uara Yesus sungguh merdu: “Yang haus, datanglah! <br><b>A</b>ku akan memberimu <br><b>a</b>ir kehidupan.”"
    },
    {
      "label": "2C",
      "num": 2,
      "html": "<b>2</b><br><b>K</b>u segra datang padaNya, <br><b>j</b>iwaku puaslah, <br><b>S</b>ungguh besar anugrahNya, <br><b>h</b>atiku gembira. "
    },
    {
      "label": "3",
      "num": 3,
      "html": "3<br><b>S</b>uara Yesus penuh kasih: “Akulah trang dunia; <br><b>D</b>i dalamKu ada terang, <br><b>b</b>agai sinar surya.”"
    },
    {
      "label": "3C",
      "num": 3,
      "html": "<b>3</b><br><b>K</b>u pandang Yesus, Tuhanku, <br><b>D</b>ialah terang hidup, <br><b>K</b>u 'kan jalan dalam trangNya, <br><b>s</b>ampai masuk surga. "
    }
  ]
}