{
    "lang": "id",
    "num": "392",
    "oldnum": "392",
    "title": "Aku Akan Pergi ke Mana Engkau Mengutusku",
    "verses": [
        {
            "label": "1",
            "num": 1,
            "html": "1<br><b>M</b>ungkin tak ke gunung yang tinggi <br><b>a</b>tau ke laut yang ganas, <br><b>A</b>tau berprang di garis depan, <br><b>T</b>uhan mengutus aku; "
        },
		{
			"label": "1C",
			"num": 1,
			"html": "<b>1</b><br><b>B</b>ila dengan lembut Dia panggil <br><b>k</b>e jalan yang tak ku tahu, <br><b>K</b>u berserah dan ku jawab, Tuhan, <br><b>k</b>u pergi turut printahMu. "
		},
		{
			"label": "1C",
			"num": 1,
			"html": "<b>1</b><br><b>K</b>u pergi turut printahMu, Tuhan, <br><b>l</b>alui gunung dan lautan; <br><b>K</b>u kan kabarkan FirmanMu, Tuhan, <br><b>j</b>adi sperti kehendakMu. "
		},
        {
            "label": "2",
            "num": 2,
            "html": "2<br><b>M</b>ungkin hari ini Dia mau ku <br><b>m</b>engabarkan kasihNya; <br><b>M</b>ungkin skarang harus ku cari <br><b>s</b>eorang yang tersesat; "
        },
		{
			"label": "2C",
			"num": 2,
			"html": "<b>2</b><br><b>T</b>uhan, bila Kau menuntunku, <br><b>k</b>abar baik trus bergema, <br><b>W</b>alau jalan gelap dan sukar, <br><b>k</b>u kan kabarkan FirmanMu. "
		},
		{
			"label": "2C",
			"num": 2,
			"html": "<b>2</b><br><b>K</b>u pergi turut printahMu, Tuhan, <br><b>l</b>alui gunung dan lautan; <br><b>K</b>u kan kabarkan FirmanMu, Tuhan, <br><b>j</b>adi sperti kehendakMu. "
		},
        {
            "label": "3",
            "num": 3,
            "html": "3<br><b>A</b>dalah tempat yang sengsara, <br><b>l</b>adang untuk menuai; <br><b>D</b>i sana ku kan giat bekerja <br><b>t</b>uk Yesus yang tersalib; "
        },
		{
			"label": "3C",
			"num": 3,
			"html": "<b>3</b><br><b>K</b>arnanya ku serahkan semua, <br><b>s</b>bab Yesus cintaku, <br><b>D</b>engan tulus ku mau bekerja, <br><b>j</b>adi sperti kehendakMu. "
		},
		{
			"label": "3C",
			"num": 3,
			"html": "<b>3</b><br><b>K</b>u pergi turut printahMu, Tuhan, <br><b>l</b>alui gunung dan lautan; <br><b>K</b>u kan kabarkan FirmanMu, Tuhan, <br><b>j</b>adi sperti kehendakMu. "
		}
		
    ]
}